{
  "id": {
    "0": "4661",
    "1": "3791",
    "2": "7510"
  },
  "名稱": {
    "0": "魔法打擊者",
    "1": "炸彈龍",
    "2": "D-HERO光碟小子"
  },
  "種類": {
    "0": "效果怪獸",
    "1": "效果怪獸",
    "2": "效果怪獸"
  },
  "屬性": {
    "0": "地",
    "1": "地",
    "2": "闇"
  },
  "等級": {
    "0": "等級3",
    "1": "等級3",
    "2": "等級1"
  },
  "種族": {
    "0": "戰士族",
    "1": "龍族",
    "2": "戰士族"
  },
  "攻擊": {
    "0": "600",
    "1": "1000",
    "2": "300"
  },
  "守備": {
    "0": "200",
    "1": "0",
    "2": "300"
  },
  "效果": {
    "0": "可以移除我方墓地的1張魔法卡當作條件從手札特殊召喚此卡。此卡可以直接攻擊。此卡進行戰鬥時給予我方的戰鬥傷害為0。",
    "1": "此卡被戰鬥破壞送入墓地時，破壞此卡的怪獸破壞。此卡攻擊的場合，雙方玩家受到的戰鬥傷害為0。",
    "2": "此卡從墓地特殊召喚成功時發動。此卡的控制者抽2張牌。"
  },
  "image_url": {
    "0": "https://storage.xpg.cards/image/EPK1/KR001.jpg",
    "1": "https://storage.xpg.cards/image/DT08/JP009.jpg",
    "2": "https://storage.xpg.cards/image/WC07/JP003.jpg"
  }
}